syndantic/__about__.py
syndantic/__init__.py
syndantic/py.typed
syndantic-1.0.1.dev1.dist-info/licenses/LICENSE
syndantic-1.0.1.dev1.dist-info/METADATA
syndantic-1.0.1.dev1.dist-info/WHEEL
syndantic-1.0.1.dev1.dist-info/top_level.txt
syndantic-1.0.1.dev1.dist-info/RECORD
