Metadata-Version: 2.4
Name: syndantic
Version: 1.0.1.dev1
Summary: AST-Driven Parsing
Author-email: tom65536 <peregrinus@planet.ms>
License: MIT License
Project-URL: Home, https://github.com/tom65536/syndantic
Project-URL: Source, https://github.com/tom65536/syndantic
Project-URL: Documentation, https://syndantic.readthedocs.io/latest/
Project-URL: Pypi, https://pypi.org/project/syndantic/
Project-URL: Issues, https://github.com/tom65536/syndantic/issues
Project-URL: Changelog, https://github.com/tom65536/syndantic/blob/main/CHANGELOG.md
Classifier: License :: OSI Approved :: MIT License
Classifier: Development Status :: 2 - Pre-Alpha
Classifier: Intended Audience :: Developers
Classifier: Intended Audience :: Education
Classifier: Programming Language :: Python :: 3.11
Classifier: Programming Language :: Python :: 3.12
Classifier: Programming Language :: Python :: 3.13
Classifier: Typing :: Typed
Requires-Python: >=3.11
License-File: LICENSE
Requires-Dist: pydantic~=2.11
Provides-Extra: build
Requires-Dist: build~=1.2; extra == "build"
Dynamic: license-file
